mailchimp_auto/__init__.py
mailchimp_auto/__main__.py
mailchimp_auto/main.py
mailchimp_auto/scripts/__init__.py
mailchimp_auto/scripts/campaign_detail.py
mailchimp_auto/scripts/Config.py
mailchimp_auto/scripts/create_campaign.py
mailchimp_auto/scripts/directory.py
mailchimp_auto/scripts/engine.py
mailchimp_auto/scripts/gspread_data.py
mailchimp_auto/scripts/image_processor.py
mailchimp_auto/scripts/load_newsletter_template.py
mailchimp_auto/scripts/template_action.py
mailchimp_auto/scripts/template_Config.py
mailchimp_auto-0.1.1.dist-info/entry_points.txt
mailchimp_auto-0.1.1.dist-info/LICENSE
mailchimp_auto-0.1.1.dist-info/METADATA
mailchimp_auto-0.1.1.dist-info/WHEEL
mailchimp_auto-0.1.1.dist-info/RECORD
