Metadata-Version: 2.1
Name: mailchimp-auto
Version: 0.1.1
Summary: 
Author: tys203831
Author-email: tys203831@gmail.com
Requires-Python: >=3.9.12,<4.0.0
Classifier: Programming Language :: Python :: 3
Classifier: Programming Language :: Python :: 3.10
Classifier: Programming Language :: Python :: 3.11
Requires-Dist: Jinja2 (>=3.1.2,<4.0.0)
Requires-Dist: Pillow (>=9.4.0,<10.0.0)
Requires-Dist: gspread (>=5.4.0,<6.0.0)
Requires-Dist: mailchimp-marketing (>=3.0.75,<4.0.0)
Requires-Dist: pandas (>=1.4.3,<2.0.0)
Requires-Dist: typer[all] (>=0.6.1,<0.7.0)
